extr_ds/__init__.py
extr_ds/labelers/__init__.py
extr_ds/labelers/iob.py
extr_ds/labelers/relation.py
extr_ds/manager/__init__.py
extr_ds/manager/cmd.py
extr_ds/manager/process/__init__.py
extr_ds/manager/process/how_to.py
extr_ds/manager/process/save.py
extr_ds/manager/process/split.py
extr_ds/manager/process/workspace.py
extr_ds/manager/process/entities/__init__.py
extr_ds/manager/process/entities/annotate.py
extr_ds/manager/process/entities/dev.py
extr_ds/manager/process/entities/models.py
extr_ds/manager/process/relations/__init__.py
extr_ds/manager/process/relations/dev.py
extr_ds/manager/process/relations/relate.py
extr_ds/manager/utils/__init__.py
extr_ds/manager/utils/filesystem.py
extr_ds/manager/utils/imports.py
extr_ds/models/__init__.py
extr_ds/models/labels.py
extr_ds/rules/__init__.py
extr_ds/rules/majority.py
extr_ds/rules/models.py
extr_ds/rules/units.py
extr_ds/transformers/__init__.py
extr_ds/transformers/iob.py
extr_ds/validators/__init__.py
extr_ds/validators/differences.py
extr_ds-0.0.86.dist-info/LICENSE
extr_ds-0.0.86.dist-info/METADATA
extr_ds-0.0.86.dist-info/WHEEL
extr_ds-0.0.86.dist-info/entry_points.txt
extr_ds-0.0.86.dist-info/top_level.txt
extr_ds-0.0.86.dist-info/RECORD
