Metadata-Version: 2.1
Name: extr-ds
Version: 0.0.86
Summary: Library to quickly build basic datasets for Named Entity Recognition (NER) and Relation Extraction (RE) Machine Learning tasks.
Home-page: https://github.com/dpasse/extr-ds
License: UNKNOWN
Platform: UNKNOWN
Requires-Dist: extr (==0.0.44)
